MANIFEST.in
README.md
requirements.txt
setup.py
mytesthello2/__init__.py
mytesthello2/help.py
mytesthello2.egg-info/PKG-INFO
mytesthello2.egg-info/SOURCES.txt
mytesthello2.egg-info/dependency_links.txt
mytesthello2.egg-info/top_level.txt