Metadata-Version: 1.0
Name: mytesthello2
Version: 0.0.1
Summary: this  is a hello test py file
Home-page: https://mytesthello1.com/
Author: prownd
Author-email: prownd12345@gmail.com
License: MIT License
Platform: UNKNOWN
